pyggc/ghcli/simple.py
pyggc/git/simple.py
pyggc-1.1.0.dist-info/LICENSE
pyggc-1.1.0.dist-info/METADATA
pyggc-1.1.0.dist-info/WHEEL
pyggc-1.1.0.dist-info/top_level.txt
pyggc-1.1.0.dist-info/RECORD
